{
    "swiperlist": [{
        "list1": [{
                "url": "../img/5.jpg",
                "text": "外卖"
            },
            {
                "url": "../img/6.jpg",
                "text": "KTV"
            },
            {
                "url": "../img/7.jpg",
                "text": "周边游"
            },
            {
                "url": "../img/8.jpg",
                "text": "丽人"
            },
            {
                "url": "../img/9.jpg",
                "text": "小吃快餐"
            },
            {
                "url": "../img/10.jpg",
                "text": "机票/火车票"
            },
            {
                "url": "../img/1.jpg",
                "text": "美食"
            },
            {
                "url": "../img/2.jpg",
                "text": "猫眼电影"
            },
            {
                "url": "../img/3.jpg",
                "text": "酒店"
            },
            {
                "url": "../img/4.jpg",
                "text": "休闲娱乐"
            }
        ]
    }, {
        "list1": [{
                "url": "../img/1.jpg",
                "text": "美食"
            },
            {
                "url": "../img/2.jpg",
                "text": "猫眼电影"
            },
            {
                "url": "../img/3.jpg",
                "text": "酒店"
            },
            {
                "url": "../img/4.jpg",
                "text": "休闲娱乐"
            },
            {
                "url": "../img/5.jpg",
                "text": "外卖"
            },
            {
                "url": "../img/6.jpg",
                "text": "KTV"
            },
            {
                "url": "../img/7.jpg",
                "text": "周边游"
            },
            {
                "url": "../img/8.jpg",
                "text": "丽人"
            },
            {
                "url": "../img/9.jpg",
                "text": "小吃快餐"
            },
            {
                "url": "../img/10.jpg",
                "text": "机票/火车票"
            }
        ]
    }]

}