{
	"tit": [
		"序号",
		"姓名",
		"年龄",
		"性别",
		"身高"
	],
	"lists": [
		{
			"name":"ABC",
			"age":"21",
			"sex":"男",
			"height":"180CM"
		},
		{
			"name":"KPL",
			"age":"21",
			"sex":"男",
			"height":"180CM"
		},
		{
			"name":"obj",
			"age":"21",
			"sex":"男",
			"height":"172CM"
		},
		{
			"name":"undefine",
			"age":"21",
			"sex":"女",
			"height":"180CM"
		},
		{
			"name":"Null",
			"age":"21",
			"sex":"男",
			"height":"180CM"
		},
		{
			"name":"Null",
			"age":"21",
			"sex":"女",
			"height":"160CM"
		},
		{
			"name":"QKG",
			"age":"20",
			"sex":"男",
			"height":"170CM"
		}
	]
}